{
  "type": "corpus",
  "trainingdata": false,
  "in_collections": [
    "kubhist2"
  ],
  "downloads": [
    {
      "url": "https://spraakbanken.gu.se/lb/resurser/meningsmangder/kubhist2-blekingsposten-1870.xml.bz2",
      "type": "corpus",
      "format": "XML",
      "info": "",
      "licence": "CC BY 4.0",
      "licence_url": "",
      "restriction": "attribution"
    },
    {
      "url": "https://svn.spraakdata.gu.se/sb-arkiv/pub/frekvens/stats_kubhist2-blekingsposten-1870.csv",
      "type": "token frequencies",
      "format": "CSV",
      "info": "",
      "licence": "CC BY 4.0",
      "licence_url": "",
      "restriction": "attribution"
    }
  ],
  "interface": [
    {
      "licence": "CC BY 4.0",
      "restriction": "attribution",
      "access": "https://spraakbanken.gu.se/korp/?mode=kubhist#corpus=kubhist2-blekingsposten-1870"
    }
  ],
  "contact_info": {
    "surname": "Forsberg",
    "givenName": "Markus",
    "email": "sb-info@svenska.gu.se",
    "affiliation": {
      "organisation": "Språkbanken",
      "email": "sb-info@svenska.gu.se"
    }
  },
  "size": {
    "tokens": "13863380",
    "sentences": "997004"
  },
  "language_codes": [
    "swe"
  ],
  "name": {
    "swe": "Blekingsposten 1870-talet",
    "eng": "Blekingsposten 1870's"
  },
  "short_description": {
    "swe": "Del av samlingen Kubhist2",
    "eng": "Part of the collection Kubhist2"
  }
}