{
  "name": {
    "swe": "Ordfrekvenser Dagens Nyheter 2004",
    "eng": "Word frequencies Dagens Nyheter 2004"
  },
  "short_description": {
    "swe": "Del av samlingen Kubord",
    "eng": "Part of the collection Kubord"
  },
  "type": "corpus",
  "trainingdata": false,
  "unlisted": false,
  "successors": [],
  "language_codes": [
    "swe"
  ],
  "size": {
    "tokens": "60004993",
    "sentences": "353"
  },
  "in_collections": [],
  "downloads": [
    {
      "url": "https://svn.spraakdata.gu.se/sb-arkiv/pub/frekvens/stats_kubord-dn-2004.csv",
      "type": "token frequencies",
      "format": "CSV",
      "info": "",
      "licence": "CC BY 4.0",
      "restriction": "attribution"
    }
  ],
  "interface": [
    {
      "access": "https://spraakbanken.gu.se/korp/?mode={'name': 'kubord', 'folder': 'dn'}#corpus=kubord-dn-2004",
      "licence": "CC BY 4.0",
      "restriction": "attribution"
    }
  ],
  "contact_info": {
    "surname": "Forsberg",
    "givenName": "Markus",
    "email": "sb-info@svenska.gu.se",
    "affiliation": {
      "organisation": "Språkbanken",
      "email": "sb-info@svenska.gu.se"
    }
  }
}