{
  "type": "corpus",
  "trainingdata": false,
  "downloads": [
    {
      "licence": "CC BY 4.0",
      "licence_url": "https://creativecommons.org/licenses/by/4.0/",
      "restriction": "attribution",
      "download": "https://svn.spraakdata.gu.se/sb-arkiv/pub/frekvens/stats_SAKPROSA1900-1959.txt",
      "type": "token frequencies",
      "format": "CSV"
    }
  ],
  "interface": [
    {
      "licence": "other",
      "restriction": "other",
      "access": "https://spraakbanken.gu.se/korp/?mode=fisk1800#corpus=sakprosa1900-1959"
    }
  ],
  "contact_info": {
    "surname": "Forsberg",
    "givenName": "Markus",
    "email": "sb-info@svenska.gu.se",
    "affiliation": {
      "organisation": "Språkbanken",
      "email": "sb-info@svenska.gu.se"
    }
  },
  "size": {
    "tokens": "346718",
    "sentences": "15529"
  },
  "language_codes": [
    "swe"
  ],
  "name": {
    "swe": "Sakprosa 1900–1959",
    "eng": "Non-fiction 1900–1959"
  },
  "short_description": {
    "swe": "Del av finlandssvensk språkbank över svenskan i Finland i dag och i går",
    "eng": "Part of the Finland Swedish language bank over Swedish in Finland today and yesterday"
  }
}