{
  "type": "lexicon",
  "trainingdata": false,
  "downloads": [
    {
      "licence": "CC BY 4.0",
      "licence_url": "https://creativecommons.org/licenses/by/4.0/",
      "restriction": "attribution",
      "download": "https://spraakbanken.gu.se/sporting/",
      "type": "other",
      "format": null
    },
    {
      "licence": "CC BY 4.0",
      "licence_url": "https://creativecommons.org/licenses/by/4.0/",
      "restriction": "attribution",
      "download": "https://spraakbanken.gu.se/sporting/",
      "type": "other",
      "format": null
    }
  ],
  "interface": [],
  "contact_info": {
    "surname": "Forsberg",
    "givenName": "Markus",
    "email": "sb-info@svenska.gu.se",
    "affiliation": {
      "organisation": "Språkbanken",
      "email": "sb-info@svenska.gu.se"
    }
  },
  "size": {
    "entries": "0"
  },
  "language_codes": [
    "swe"
  ],
  "name": {
    "swe": "Sportanglicismer",
    "eng": "Sports anglicisms"
  },
  "short_description": {
    "swe": "Engelska lånord i svenska sportspalter",
    "eng": "English loan-words in the Swedish sports press"
  }
}